native_dumper/version.py
native_dumper/__init__.py
native_dumper/dumper.py
native_dumper/common/diagram.py
native_dumper/common/pyo3http.cpython-313-darwin.so
native_dumper/common/__init__.py
native_dumper/common/logger.py
native_dumper/common/columns.py
native_dumper/common/defines.py
native_dumper/common/connector.py
native_dumper/common/writer.py
native_dumper/common/pyo3http.pyi
native_dumper/common/errors.py
native_dumper/common/multiquery.py
native_dumper/common/cursor.py
native_dumper/common/pyo3http/Cargo.toml
native_dumper/common/pyo3http/src/lib.rs
native_dumper-0.3.5.2.dist-info/RECORD
native_dumper-0.3.5.2.dist-info/WHEEL
native_dumper-0.3.5.2.dist-info/top_level.txt
native_dumper-0.3.5.2.dist-info/METADATA
native_dumper-0.3.5.2.dist-info/licenses/LICENSE
