Metadata-Version: 2.4
Name: native-dumper
Version: 0.3.5.2
Summary: Library for read and write Native format between Clickhouse and file.
Home-page: https://0xmihalich.github.io/dbhose_airflow/classes/native_dumper/index.html
Author: 0xMihalich
Author-email: bayanmobile87@gmail.com
Classifier: Development Status :: 4 - Beta
Classifier: Intended Audience :: Developers
Classifier: Programming Language :: Python :: 3.10
Classifier: Programming Language :: Python :: 3.11
Classifier: Programming Language :: Python :: 3.12
Classifier: Programming Language :: Python :: 3.13
Classifier: Programming Language :: Python :: 3.14
Requires-Python: >=3.10
License-File: LICENSE
Requires-Dist: light-compressor==0.0.2.2
Requires-Dist: nativelib==0.2.2.6
Requires-Dist: sqlparse>=0.5.5
Dynamic: author
Dynamic: author-email
Dynamic: classifier
Dynamic: description
Dynamic: description-content-type
Dynamic: home-page
Dynamic: license-file
Dynamic: requires-dist
Dynamic: requires-python
Dynamic: summary
